ndx_icephys_meta/__init__.py
ndx_icephys_meta/icephys.py
ndx_icephys_meta/io/__init__.py
ndx_icephys_meta/io/icephys.py
ndx_icephys_meta/spec/ndx-icephys-meta.extensions.yaml
ndx_icephys_meta/spec/ndx-icephys-meta.namespace.yaml
ndx_icephys_meta/test/__init__.py
ndx_icephys_meta/test/test_icephys.py
ndx_icephys_meta-0.1.0.dist-info/LICENSE.txt
ndx_icephys_meta-0.1.0.dist-info/METADATA
ndx_icephys_meta-0.1.0.dist-info/WHEEL
ndx_icephys_meta-0.1.0.dist-info/top_level.txt
ndx_icephys_meta-0.1.0.dist-info/RECORD
